{
    "飞轮舱1_变压器超温跳闸": {
        "DB": "25",
        "Start": "0.0",
        "Type": "BIT"
    },
    "飞轮舱1_变压器高温报警": {
        "DB": "25",
        "Start": "0.1",
        "Type": "BIT"
    },
    "飞轮舱1_变压器室超温报警": {
        "DB": "25",
        "Start": "0.2",
        "Type": "BIT"
    },
    "飞轮舱1_变压器温控仪故障报警": {
        "DB": "25",
        "Start": "0.5",
        "Type": "BIT"
    },
    "飞轮舱1_风机电源分位报警": {
        "DB": "25",
        "Start": "0.6",
        "Type": "BIT"
    },
    "飞轮舱1_箱变温控电源分位": {
        "DB": "25",
        "Start": "0.7",
        "Type": "BIT"
    },
    "飞轮舱1_高压断路器合位": {
        "DB": "25",
        "Start": "1.0",
        "Type": "BIT"
    },
    "飞轮舱1_低压框架QF1合闸位置": {
        "DB": "25",
        "Start": "1.2",
        "Type": "BIT"
    },
    "飞轮舱1_低压框架QF1分闸位置": {
        "DB": "25",
        "Start": "1.3",
        "Type": "BIT"
    },
    "飞轮舱1_低压框架QF2合闸位置": {
        "DB": "25",
        "Start": "1.4",
        "Type": "BIT"
    },
    "飞轮舱1_低压框架QF2分闸位置": {
        "DB": "25",
        "Start": "1.5",
        "Type": "BIT"
    },
    "飞轮舱1_门禁信号": {
        "DB": "25",
        "Start": "1.6",
        "Type": "BIT"
    },
    "飞轮舱1_低压框架QF1故障": {
        "DB": "25",
        "Start": "1.7",
        "Type": "BIT"
    },
    "飞轮舱1_UPS失电信号": {
        "DB": "25",
        "Start": "2.0",
        "Type": "BIT"
    },
    "飞轮舱1_隔离合位": {
        "DB": "25",
        "Start": "2.2",
        "Type": "BIT"
    },
    "飞轮舱1_隔离分位": {
        "DB": "25",
        "Start": "2.3",
        "Type": "BIT"
    },
    "飞轮舱1_地刀合位": {
        "DB": "25",
        "Start": "2.4",
        "Type": "BIT"
    },
    "飞轮舱1_地刀分位": {
        "DB": "25",
        "Start": "2.5",
        "Type": "BIT"
    },
    "飞轮舱1_1浪涌异常信号": {
        "DB": "25",
        "Start": "2.6",
        "Type": "BIT"
    },
    "飞轮舱1_2浪涌异常信号": {
        "DB": "25",
        "Start": "2.7",
        "Type": "BIT"
    },
    "飞轮舱1_变压器室风机启动信号": {
        "DB": "25",
        "Start": "3.0",
        "Type": "BIT"
    },
    "飞轮舱1_变压器本体风机启动信号": {
        "DB": "25",
        "Start": "3.1",
        "Type": "BIT"
    },
    "飞轮舱1_低压室风机启动信号": {
        "DB": "25",
        "Start": "3.2",
        "Type": "BIT"
    },
    "飞轮舱1_低压框架QF2故障": {
        "DB": "25",
        "Start": "3.3",
        "Type": "BIT"
    },
    "飞轮舱1_温湿度控制器": {
        "DB": "25",
        "Start": "4.2",
        "Type": "BIT"
    },
    "飞轮舱1_干变温控器": {
        "DB": "25",
        "Start": "4.3",
        "Type": "BIT"
    },
    "飞轮舱1_低压1电度表": {
        "DB": "25",
        "Start": "4.4",
        "Type": "BIT"
    },
    "飞轮舱1_低压2电度表": {
        "DB": "25",
        "Start": "4.5",
        "Type": "BIT"
    },
    "飞轮舱1_1低压侧IA1": {
        "DB": "25",
        "Start": "6.0",
        "Type": "SHORT"
    },
    "飞轮舱1_1低压侧IB1": {
        "DB": "25",
        "Start": "8.0",
        "Type": "SHORT"
    },
    "飞轮舱1_1低压侧IC1": {
        "DB": "25",
        "Start": "10.0",
        "Type": "SHORT"
    },
    "飞轮舱1_1低压侧UAB1": {
        "DB": "25",
        "Start": "12.0",
        "Type": "SHORT"
    },
    "飞轮舱1_1低压侧UBC1": {
        "DB": "25",
        "Start": "14.0",
        "Type": "SHORT"
    },
    "飞轮舱1_1低压侧UCA1": {
        "DB": "25",
        "Start": "16.0",
        "Type": "SHORT"
    },
    "飞轮舱1_1低压侧P1": {
        "DB": "25",
        "Start": "18.0",
        "Type": "SHORT"
    },
    "飞轮舱1_1低压侧Q1": {
        "DB": "25",
        "Start": "20.0",
        "Type": "SHORT"
    },
    "飞轮舱1_1低压侧COS1": {
        "DB": "25",
        "Start": "22.0",
        "Type": "SHORT"
    },
    "飞轮舱1_1低压侧F1": {
        "DB": "25",
        "Start": "24.0",
        "Type": "SHORT"
    },
    "飞轮舱1_2低压侧IA2": {
        "DB": "25",
        "Start": "26.0",
        "Type": "SHORT"
    },
    "飞轮舱1_2低压侧IB2": {
        "DB": "25",
        "Start": "28.0",
        "Type": "SHORT"
    },
    "飞轮舱1_2低压侧IC2": {
        "DB": "25",
        "Start": "30.0",
        "Type": "SHORT"
    },
    "飞轮舱1_2低压侧UAB2": {
        "DB": "25",
        "Start": "32.0",
        "Type": "SHORT"
    },
    "飞轮舱1_2低压侧UBC2": {
        "DB": "25",
        "Start": "34.0",
        "Type": "SHORT"
    },
    "飞轮舱1_2低压侧UCA2": {
        "DB": "25",
        "Start": "36.0",
        "Type": "SHORT"
    },
    "飞轮舱1_2低压侧P2": {
        "DB": "25",
        "Start": "38.0",
        "Type": "SHORT"
    },
    "飞轮舱1_2低压侧Q2": {
        "DB": "25",
        "Start": "40.0",
        "Type": "SHORT"
    },
    "飞轮舱1_2低压侧COS2": {
        "DB": "25",
        "Start": "42.0",
        "Type": "SHORT"
    },
    "飞轮舱1_高压侧IA3": {
        "DB": "25",
        "Start": "44.0",
        "Type": "SHORT"
    },
    "飞轮舱1_高压侧IB3": {
        "DB": "25",
        "Start": "46.0",
        "Type": "SHORT"
    },
    "飞轮舱1_高压侧IC3": {
        "DB": "25",
        "Start": "48.0",
        "Type": "SHORT"
    },
    "飞轮舱1_箱变A相绕组温度": {
        "DB": "25",
        "Start": "50.0",
        "Type": "SHORT"
    },
    "飞轮舱1_箱变B相绕组温度": {
        "DB": "25",
        "Start": "52.0",
        "Type": "SHORT"
    },
    "飞轮舱1_箱变C相绕组温度": {
        "DB": "25",
        "Start": "54.0",
        "Type": "SHORT"
    },
    "飞轮舱1_环境温度": {
        "DB": "25",
        "Start": "60.0",
        "Type": "SHORT"
    },
    "飞轮舱1_环境湿度": {
        "DB": "25",
        "Start": "62.0",
        "Type": "SHORT"
    },
    "飞轮舱1_温控器A相绕组温度": {
        "DB": "25",
        "Start": "64.0",
        "Type": "SHORT"
    },
    "飞轮舱1_温控器B相绕组温度": {
        "DB": "25",
        "Start": "66.0",
        "Type": "SHORT"
    },
    "飞轮舱1_温控器C相绕组温度": {
        "DB": "25",
        "Start": "68.0",
        "Type": "SHORT"
    },
    "飞轮舱1_低压1吸收有功": {
        "DB": "25",
        "Start": "70.0",
        "Type": "LONG"
    },
    "飞轮舱1_低压1释放有功": {
        "DB": "25",
        "Start": "74.0",
        "Type": "LONG"
    },
    "飞轮舱1_低压1感性无功": {
        "DB": "25",
        "Start": "78.0",
        "Type": "LONG"
    },
    "飞轮舱1_低压1容性无功": {
        "DB": "25",
        "Start": "82.0",
        "Type": "LONG"
    },
    "飞轮舱1_低压2吸收有功": {
        "DB": "25",
        "Start": "86.0",
        "Type": "LONG"
    },
    "飞轮舱1_低压2释放有功": {
        "DB": "25",
        "Start": "90.0",
        "Type": "LONG"
    },
    "飞轮舱1_低压2感性无功": {
        "DB": "25",
        "Start": "94.0",
        "Type": "LONG"
    },
    "飞轮舱1_低压2容性无功": {
        "DB": "25",
        "Start": "98.0",
        "Type": "LONG"
    }
}